Workbook

Sheet Justification
A1: Coûts des arrêts de bus et des stations vélo — d’où viennent les chiffres
A2: Même principe que pour Citiz : aucun jeu de données ouvert ne donne ces coûts. On part de documents publics, on calcule un coût annuel complet (comparable au coût annuel d’une station Citiz), puis on vérifie avec d’autres repères.
A4: Chiffre | B4: Valeur (défaut) | C4: D’où il vient | D4: Comment on l’obtient
A5: ARRÊT DE BUS
A6: Coût d’installation | B6: 10 950 € | C6: Chiffrage de voirie d’une commune belge (Fléron, 2023) | D6: Arrêt accessible 8 750 € + abribus 2 200 €. Bas : 5 500 € (quai simple). Haut : 31 500 € (moyenne par arrêt de la mise en accessibilité à Marseille : 83,5 M€ ÷ 2 650 arrêts).
A7: Vérification | B7: ≈ 6 760 € | C7: Délibération d’Annemasse Agglo (2025) | D7: 2 quais accessibles avec abribus ≈ 13 500 € : le chiffre tombe bien dans notre fourchette.
A8: Durée de vie | B8: 20 ans | C8: Durée comptable des « installations de voirie » dans les budgets communaux | D8: Durée officielle utilisée par les collectivités pour amortir ce type d’aménagement.
A9: Coût annuel | B9: 548 € | C9: Calcul | D9: 10 950 € ÷ 20 ans. Pas de coût de bus en plus : on ajoute un arrêt sur une ligne qui passe déjà.
A10: STATION VÉLO
A11: Contrat VélôToulouse | B11: 97 M€ sur 12 ans | C11: Contrat signé par Toulouse avec JCDecaux en 2023 (France Bleu, JCDecaux) | D11: Coût réel payé à Toulouse aujourd’hui, pour 3 300 vélos (dont la moitié électriques) et 400 stations.
A12: Coût par vélo et par an | B12: 2 449 € | C12: Calcul | D12: 97 M€ ÷ 12 ans ÷ 3 300 vélos. Bas : 2 113 € si le contrat passe à 3 825 vélos. Haut : 3 000 € (haut de la fourchette nationale du GART).
A13: Coût annuel d’une station | B13: 24 495 € | C13: Calcul | D13: 2 449 € × 10 vélos (taille choisie par l’équipe ; la moyenne toulousaine est de 8,25 vélos par station).
A14: Vérification | B14: 2 000 à 3 000 € | C14: Ancien contrat VélôToulouse (~2013) et enquête nationale du GART | D14: Notre 2 449 € est dans la fourchette, et un peu au-dessus de l’ancien contrat toulousain (2 000 €) : logique, la moitié des vélos sont maintenant électriques.
A15: À RETENIR
A16: Comparaison | B16: Bus 548 € / Citiz 19 486 € / Vélo 24 495 € par an | C16: — | D16: Ajouter un arrêt est de loin le moins cher, mais ce n’est possible que là où une ligne passe déjà : pour le bus, la contrainte est l’emplacement, pas le coût.
A18: Calculs détaillés : onglet « Calcul ». Citations exactes et liens : onglet « Hypothèses ».

Sheet Hypothèses
A1: Réf | B1: Paramètre | C1: Valeur | D1: Unité | E1: Type | F1: Citation exacte ou justification | G1: Lien vers la source | H1: Date
A2: ARRÊT DE BUS (ajouté sur une ligne existante)
A3: B1 | B3: Quai bus en avancée de trottoir | C3: 5500 | D3: € HT par arrêt | E3: Sourcé | F3: « quai bus en avancée ou extension de trottoir 5.500,00 » (chiffrage de voirie, Fléron, Belgique) | G3: Ouvrir la source | H3: 2023
A4: B2 | B4: Aménagement d’un arrêt accessible (PMR) | C4: 8750 | D4: € HT par arrêt | E4: Sourcé | F4: « Aménagement des arrêts bus PMR* 8.750,00 » | G4: Ouvrir la source | H4: 2023
A5: B3 | B5: Abribus | C5: 2200 | D5: € HT par arrêt | E5: Sourcé | F5: « aménagement d’un abribus […] 2200 € sans subvention » | G5: Ouvrir la source | H5: 2023
A6: B4 | B6: Mise en accessibilité du réseau de Marseille | C6: 83500000 | D6: € pour le réseau | E6: Sourcé | F6: « Des travaux dont le coût était chiffré à 83,5 millions d’euros sur 10 ans » | G6: Ouvrir la source | H6: 2016
A7: B5 | B7: Nombre d’arrêts concernés à Marseille | C7: 2650 | D7: arrêts | E7: Sourcé | F7: « plus de 150 arrêts de BHNS et presque 2 500 autres arrêts de bus » : 150 + 2 500 | G7: Ouvrir la source | H7: 2016
A8: B6 | B8: Durée d’amortissement d’un arrêt | C8: 20 | D8: ans | E8: Sourcé | F8: Durée comptable des « Installations de voirie » dans une délibération communale (nomenclature M57) : 20 ans | G8: Ouvrir la source | H8: 2023
A9: B7 | B9: Contrôle : 2 quais accessibles avec abribus (Annemasse) | C9: 13518 | D9: € HT pour 2 arrêts | E9: Sourcé | F9: Abribus 2 688 € + quai 4 845 € + bordure 5 985 € | G9: Ouvrir la source | H9: 2025
A10: STATION VÉLO (VélôToulouse)
A11: V1 | B11: Montant du contrat VélôToulouse | C11: 97000000 | D11: € sur toute la durée | E11: Sourcé | F11: « Le montant du contrat est de 97 millions d’euros pour 12 ans » | G11: Ouvrir la source | H11: 2023
A12: V2 | B12: Durée du contrat | C12: 12 | D12: ans | E12: Sourcé | F12: Contrat de 12 ans signé avec JCDecaux en septembre 2023 | G12: Ouvrir la source | H12: 2023
A13: V3 | B13: Vélos en service (déploiement 2024) | C13: 3300 | D13: vélos | E13: Sourcé | F13: « Ce sont 3300 nouveaux vélos » et « 400 stations », dont 50 % à assistance électrique | G13: Ouvrir la source | H13: 2024
A14: V4 | B14: Vélos après extension possible du contrat | C14: 3825 | D14: vélos | E14: Sourcé | F14: « may evolve in the future to include the provision of 3,825 bikes and 475 stations » | G14: Ouvrir la source | H14: 2023
A15: V5 | B15: Stations en service (déploiement 2024) | C15: 400 | D15: stations | E15: Sourcé | F15: « 400 stations ont été déployées » | G15: Ouvrir la source | H15: 2024
A16: V6 | B16: Coût moyen national, haut de fourchette | C16: 3000 | D16: € par vélo et par an | E16: Sourcé | F16: Enquête du GART : « entre 2.000 et 3.000 euros par vélo et par an » (investissement, exploitation, maintenance) | G16: Ouvrir la source | H16: 2010
A17: V7 | B17: Vélos par station retenus | C17: 10 | D17: vélos | E17: Hypothèse équipe | F17: Taille type d’une nouvelle station (la moyenne toulousaine est de 3 300 ÷ 400 = 8,25 vélos) | G17: — | H17: —
A18: V8 | B18: Repère : ancien contrat VélôToulouse | C18: 2000 | D18: € par vélo et par an | E18: Sourcé | F18: « 4,7 millions d’euros par an, ce qui revient à 2000 euros par vélo et par an » | G18: Ouvrir la source | H18: vers 2013
A19: V9 | B19: Repère : achat d’une station neuve de 10 vélos (Mulhouse) | C19: 45000 | D19: € (milieu de 40 000 à 50 000 €) | E19: Sourcé | F19: « compris entre 40.000€ et 50.000€ pour une station et 10 vélos » (investissement seul) | G19: Ouvrir la source | H19: 2024
A21: Chiffres en bleu = données d’entrée (modifiables). Fond orange = hypothèse de l’équipe.

Sheet Calcul
A1: Poste | B1: Bas | C1: Défaut | D1: Haut | E1: Formule
A2: 1. ARRÊT DE BUS : INVESTISSEMENT
A3: Coût d’installation d’un arrêt | B3: =Hypothèses!$C$3 -> 5500 | C3: =Hypothèses!$C$4+Hypothèses!$C$5 -> 10950 | D3: =Hypothèses!$C$6/Hypothèses!$C$7 -> 31509.434 | E3: Bas : quai simple. Défaut : arrêt accessible + abribus. Haut : moyenne Marseille (travaux lourds)
A4: Contrôle Annemasse, par arrêt | B4: =Hypothèses!$C$9/2 -> 6759 | C4: =Hypothèses!$C$9/2 -> 6759 | D4: =Hypothèses!$C$9/2 -> 6759 | E4: B7 ÷ 2 : doit tomber dans la fourchette
A5: 2. ARRÊT DE BUS : COÛT ANNUEL
A6: Coût annuel d’un arrêt (investissement amorti) | B6: =B3/Hypothèses!$C$8 -> 275 | C6: =C3/Hypothèses!$C$8 -> 547.5 | D6: =D3/Hypothèses!$C$8 -> 1575.4717 | E6: Investissement ÷ 20 ans. Pas de bus supplémentaire : la ligne existe déjà
A7: 3. STATION VÉLO : COÛT PAR VÉLO ET PAR AN
A8: Coût annuel complet d’un vélo | B8: =Hypothèses!$C$11/Hypothèses!$C$12/Hypothèses!$C$14 -> 2113.2898 | C8: =Hypothèses!$C$11/Hypothèses!$C$12/Hypothèses!$C$13 -> 2449.4949 | D8: =Hypothèses!$C$16 -> 3000 | E8: Bas : contrat ÷ 12 ans ÷ 3 825 vélos. Défaut : contrat ÷ 12 ans ÷ 3 300 vélos. Haut : GART
A9: 4. STATION VÉLO : COÛT ANNUEL D’UNE STATION
A10: Coût annuel complet d’une station de 10 vélos | B10: =B8*Hypothèses!$C$17 -> 21132.898 | C10: =C8*Hypothèses!$C$17 -> 24494.949 | D10: =D8*Hypothèses!$C$17 -> 30000 | E10: Coût par vélo × 10
A11: Pour info : coût annuel moyen d’une station VélôToulouse | B11: =Hypothèses!$C$11/Hypothèses!$C$12/Hypothèses!$C$15 -> 20208.333 | C11: =Hypothèses!$C$11/Hypothèses!$C$12/Hypothèses!$C$15 -> 20208.333 | D11: =Hypothèses!$C$11/Hypothèses!$C$12/Hypothèses!$C$15 -> 20208.333 | E11: Contrat ÷ 12 ans ÷ 400 stations (8,25 vélos en moyenne)
A12: 5. VÉRIFICATION DU COÛT PAR VÉLO
A13: Repère : ancien contrat VélôToulouse | B13: =Hypothèses!$C$18 -> 2000 | C13: =Hypothèses!$C$18 -> 2000 | D13: =Hypothèses!$C$18 -> 2000 | E13: Notre défaut doit être proche, un peu plus élevé (vélos électriques)
A14: Repère : fourchette nationale GART | B14: 2000 | C14: 2500 | D14: =Hypothèses!$C$16 -> 3000 | E14: 2 000 à 3 000 € par vélo et par an
