Workbook

Sheet Synthèse
A1: Coût d’une station Citiz (2 voitures) — synthèse
A2: Aucun chiffre officiel n’a été communiqué par Citiz : ces montants sont reconstitués à partir de documents publics (onglet Hypothèses) et vérifiés avec trois repères indépendants.
A4: Indicateur | B4: Bas | C4: Défaut | D4: Haut | E4: À quoi il sert
A5: Investissement à l’ouverture (station hybride) | B5: =Calcul!B6 -> 32000 | C5: =Calcul!C6 -> 58180 | D5: =Calcul!D6 -> 62200 | E5: Ce que coûte l’ouverture : place, boîtiers, achat des 2 voitures
A6: Investissement à l’ouverture (station électrique) | B6: =Calcul!B8 -> 37800 | C6: =Calcul!C8 -> 65580 | D6: =Calcul!D8 -> 71200 | E6: Idem + borne de recharge
A7: Coût annuel complet par voiture | B7: =Calcul!B16 -> 6098.54 | C7: =Calcul!C16 -> 10373.062 | D7: =Calcul!D16 -> 13211.76 | E7: Comparer avec les repères Citiz (8 500 à 10 000 € par voiture)
A8: Coût annuel complet par station | B8: =Calcul!B20 -> 12197.08 | C8: =Calcul!C20 -> 20986.124 | D8: =Calcul!D20 -> 26663.52 | E8: À UTILISER DANS L’OPTIMISATION (comparable au coût annuel des vélos)
A9: Coût annuel complet par station électrique | B9: =Calcul!B22 -> 13357.08 | C9: =Calcul!C22 -> 22466.124 | D9: =Calcul!D22 -> 28463.52 | E9: Si la station est électrique
A10: Total décaissé la première année | B10: =Calcul!B26 -> 37797.08 | C10: =Calcul!C26 -> 67530.124 | D10: =Calcul!D26 -> 76423.52 | E10: Pour le business case : effort financier de départ
A12: Comment lire : « Défaut » = valeur pour la démo ; « Bas » et « Haut » = fourchette pour tester la solidité de la recommandation.
A13: Vérification (onglet Calcul, section 5) : en valeur par défaut, notre coût par voiture (10 373 €) est dans le seuil de rentabilité donné par Citiz à l’équipe (700 à 900 € par mois, soit 8 400 à 10 800 € par an) et proche de ses montants réels (8 520 à 10 000 €). En valeur basse, l’écart correspond aux frais de structure non chiffrés (personnel, plateforme, assistance, nettoyage). La valeur haute dépasse les repères : c’est un plafond prudent.
A14: Limites : chiffres issus d’autres territoires (Genevois français, Belgique) ou de moyennes nationales ; coefficient d’usure et durée d’amortissement du boîtier = hypothèses de l’équipe ; recettes non déduites (le coût présenté est un coût brut, avant recettes des locations).

Sheet Justification
A1: D’où viennent les chiffres (valeurs par défaut)
A2: Principe : Citiz ne publie pas ses coûts et aucun jeu de données ouvert ne les contient. On reconstitue donc le coût d’une station comme dans un business plan : on liste tout ce qu’elle coûte, on trouve un prix public pour chaque poste, puis on vérifie le total avec ce que Citiz facture réellement.
A4: Chiffre | B4: Valeur | C4: D’où il vient | D4: Comment on l’obtient
A5: ÉTAPE 1 — CE QU’ON PAIE À L’OUVERTURE
A6: Voitures par station | B6: 2 | C6: Convention signée par Citiz avec le Genevois français | D6: Citiz y écrit qu’une station a besoin de 2 voitures pour être attractive.
A7: Aménagement de la place | B7: 1 200 € | C7: Dossier de presse du lancement de Citiz (2016) ; réponse de Citiz à l’équipe (2026) | D7: Peinture au sol + panneau. Bas : 0 €, car selon Citiz certaines collectivités prennent en charge l’aménagement.
A8: Boîtier électronique | B8: 4 000 € HT par voiture | C8: Même convention Citiz | D8: Boîtier qui ouvre la voiture avec la carte ou l’appli. Montant donné tel quel.
A9: Prix d’une voiture | B9: 24 490 € | C9: Prix catalogue 2026 de la Toyota Yaris hybride | D9: Citiz utilise des Yaris et des Clio. Bas : 12 000 € (bas de la fourchette du Cerema, organisme public). Haut : 26 500 € (Yaris version professionnelle).
A10: Investissement total | B10: 58 180 € | C10: Calcul | D10: 1 200 + 2 × 4 000 + 2 × 24 490.
A11: ÉTAPE 2 — CE QUE COÛTE UNE VOITURE CHAQUE ANNÉE
A12: Amortissement de la voiture | B12: 4 898 € | C12: Durée de 5 ans retenue par le Cerema pour une voiture d’autopartage | D12: 24 490 € ÷ 5 ans.
A13: Amortissement du boîtier | B13: 800 € | C13: Hypothèse de l’équipe : même durée que la voiture | D13: 4 000 € ÷ 5 ans.
A14: Assurance tous risques | B14: 1 102 € | C14: Étude des primes d’assurance auto 2025 (MoneyVox) | D14: Prime moyenne sans bonus. Bas : 610 € (conducteur expérimenté). Haut : 2 237 € (jeune conducteur). Une voiture partagée a des conducteurs de tous profils.
A15: Entretien | B15: 792 € | C15: Budget automobile 2025 (Fiches-auto) + hypothèse de l’équipe | D15: 528 € par an pour une voiture moyenne × 1,5, car une voiture partagée roule environ 2 fois plus.
A16: Kilométrage | B16: 22 000 km par an | C16: Guide de la Région wallonne sur l’autopartage (CeMathèque) | D16: Une voiture partagée devient rentable autour de 20 000 à 24 000 km par an : on prend le milieu.
A17: Carburant | B17: 2 031 € | C17: Consommation officielle de la Yaris (4,1 à 4,5 L/100 km) et prix moyen du SP95-E10 le 12/10/2026 (2,147 €/L) | D17: 22 000 km × 4,3 L ÷ 100 × 2,147 €.
A18: Redevance de stationnement | B18: 750 € | C18: Réponse de Citiz à l’équipe (20/10/2026) | D18: Citiz indique une « grande variabilité » : de 0 € à 1 500 € par an selon les accords avec la collectivité ou le parking. On prend le milieu, avec 1 place par voiture.
A19: Coût annuel par voiture | B19: 10 373 € | C19: Calcul | D19: 4 898 + 800 + 1 102 + 792 + 2 031 + 750.
A20: ÉTAPE 3 — COÛT ANNUEL D’UNE STATION
A21: Coût annuel par station | B21: 20 986 € | C21: Calcul | D21: 2 voitures × 10 373 € + aménagement amorti (1 200 € ÷ 5 ans).
A22: ÉTAPE 4 — VÉRIFICATION AVEC CE QUE CITIZ FACTURE RÉELLEMENT
A23: Repère 1 | B23: 9 000 € par voiture et par an | C23: Convention Citiz avec le Genevois français (2021) | D23: Citiz facture une voiture tout compris 750 € par mois à la collectivité : 750 × 12.
A24: Repère 2 | B24: 8 520 € par voiture et par an | C24: Dossier de presse Citiz (2016) | D24: Même chose en 2016 : 710 € par mois × 12.
A25: Repère 3 | B25: 10 000 € par voiture et par an | C25: Article de la Gazette du Midi sur Citiz Occitanie (2024) | D25: 2 M€ de chiffre d’affaires ÷ 200 voitures. Citiz est une coopérative : ses recettes couvrent à peu près ses coûts.
A26: Repère 4 (donné par Citiz) | B26: 8 400 à 10 800 € par voiture et par an | C26: Réponse de Citiz à l’équipe (20/10/2026) | D26: Citiz indique qu’une voiture est rentable à partir de 700 à 900 € de recettes par mois, selon le modèle et l’emplacement : 700 × 12 à 900 × 12.
A27: Conclusion | B27: 9 623 à 10 373 € : dans le seuil de Citiz | C27: — | D27: Notre coût par voiture (9 623 € sans redevance, 10 373 € avec) tombe dans le seuil de rentabilité donné par Citiz lui-même (8 400 à 10 800 €), et à côté de ses montants réels. L’estimation est confirmée par l’opérateur.
A29: Les citations exactes et les liens de chaque source sont dans l’onglet « Hypothèses ».

Sheet Hypothèses
A1: Réf | B1: Paramètre | C1: Bas | D1: Défaut | E1: Haut | F1: Unité | G1: Type | H1: Citation exacte ou justification | I1: Lien vers la source | J1: Date
A2: INVESTISSEMENT (à l’ouverture de la station)
A3: P1 | B3: Voitures par station | C3: 2 | D3: 2 | E3: 2 | F3: voitures | G3: Sourcé | H3: « La mise en place d’une station nécessite l’installation de 2 voitures pour que le service soit attractif » | I3: Ouvrir la source | J3: jusqu’au 31/10/2024
A4: P2 | B4: Aménagement de la place (peinture + mât) | C4: 0 | D4: 1200 | E4: 1200 | F4: € par station | G4: Sourcé | H4: Défaut et haut : « Aménagement de la station : 1 200€ (peinture + mât) » (2016). Bas : 0 €, car selon Citiz « certaines collectivités prennent en charge les aménagements, d’autres non » (réponse de Citiz à l’équipe, 20/10/2026) | I4: Ouvrir la source | J4: 2016 / 2026
A5: P3 | B5: Boîtier télématique (ouverture, réservation) | C5: 4000 | D5: 4000 | E5: 4000 | F5: € HT par voiture | G5: Sourcé | H5: « coût d’achat 4000 € HT / boitier » | I5: Ouvrir la source | J5: jusqu’au 31/10/2024
A6: P4 | B6: Prix d’achat d’une voiture | C6: 12000 | D6: 24490 | E6: 26500 | F6: € par voiture | G6: Sourcé | H6: Bas : Cerema « Coût des véhicules (en achat ou en LLD) : entre 12k€ et 20k€ ». Défaut : Yaris hybride 2026 « Prix à partir de 24 490 € ». Haut : Yaris Affaires 26 500 € (L’argus). Citiz utilise des Yaris et des Clio. | I6: Ouvrir la source | J6: 2020 / 2026
A7: P5 | B7: Durée d’amortissement d’une voiture | C7: 5 | D7: 5 | E7: 5 | F7: ans | G7: Sourcé | H7: « Véhicule (LLD ou achat, amorti sur environ 5 ans) » | I7: Ouvrir la source | J7: 2020
A8: P6 | B8: Durée d’amortissement du boîtier et de l’aménagement | C8: 5 | D8: 5 | E8: 5 | F8: ans | G8: Hypothèse équipe | H8: Alignée sur la durée de vie de la voiture (pas de source) | I8: — | J8: —
A9: FONCTIONNEMENT (par voiture et par an)
A10: P7 | B10: Assurance tous risques | C10: 610 | D10: 1102 | E10: 2237 | F10: € par voiture et par an | G10: Sourcé | H10: Bas : « tous risques : environ 610 €/an pour un conducteur expérimenté ». Défaut : 1 102 €/an « sans bonus ». Haut : « 2 237 €/an pour un jeune conducteur ». Une voiture partagée a des conducteurs de tous profils. | I10: Ouvrir la source | J10: 2025
A11: P8 | B11: Entretien et réparations (voiture moyenne) | C11: 528 | D11: 528 | E11: 528 | F11: € par voiture et par an | G11: Sourcé | H11: 44 €/mois d’entretien pour une voiture thermique (budget automobile 2025), soit 528 €/an | I11: Ouvrir la source | J11: 2025
A12: P9 | B12: Coefficient d’usure d’une voiture partagée | C12: 1 | D12: 1.5 | E12: 2 | F12: × entretien moyen | G12: Hypothèse équipe | H12: Une voiture partagée roule environ 2 fois plus qu’une voiture particulière (P10) et a plusieurs conducteurs (pas de source directe) | I12: — | J12: —
A13: P10 | B13: Kilométrage annuel d’une voiture partagée | C13: 20000 | D13: 22000 | E13: 24000 | F13: km par an | G13: Sourcé | H13: « Le seuil de rentabilité (citadine) se situe autour de 20 à 24.000 km/an » | I13: Ouvrir la source | J13: 2022
A14: P11 | B14: Consommation (Toyota Yaris hybride) | C14: 4.1 | D14: 4.3 | E14: 4.5 | F14: L / 100 km | G14: Sourcé | H14: « La Yaris annonce 4,1 à 4,5 L/100 km en cycle WLTP » | I14: Ouvrir la source | J14: 2026
A15: P12 | B15: Prix du carburant (SP95-E10) | C15: 2.147 | D15: 2.147 | E15: 2.147 | F15: € par litre | G15: Sourcé | H15: Prix moyen national SP95-E10 le 12 octobre 2026 : 2,147 €/L | I15: Ouvrir la source | J15: 12/10/2026
A16: P13 | B16: Redevance de stationnement (place) | C16: 0 | D16: 750 | E16: 1500 | F16: € par place et par an | G16: Sourcé (Citiz) | H16: Réponse de Citiz à l’équipe (20/10/2026) : « Grande variabilité sur le coût de redevance » ; « en parking, existence ou non d’accords commerciaux (on va de 0 € à 1 500 € / an) ». Défaut = milieu de la fourchette. On suppose 1 place = 1 voiture (à confirmer avec Citiz). | I16: — | J16: 20/10/2026
A17: OPTION : STATION ÉLECTRIQUE
A18: P14 | B18: Borne 22 kW, 2 points de charge (achat) | C18: 3300 | D18: 3650 | E18: 4000 | F18: € HT par station | G18: Sourcé | H18: « Comptez entre 3 300 € et 4 000 € HT (hors installation) » | I18: Ouvrir la source | J18: 2024
A19: P15 | B19: Installation de la borne | C19: 2500 | D19: 3750 | E19: 5000 | F19: € par station | G19: Sourcé | H19: Coût moyen d’installation d’une borne 22 kW : 2 500 € à 5 000 €. À Niort, les bornes des stations Citiz sont à la charge de la collectivité. | I19: Ouvrir la source | J19: 2024
A20: REPÈRES POUR VÉRIFIER (coût complet constaté, par voiture et par an)
A21: R1 | B21: Recettes Citiz Occitanie par voiture | C21: 10000 | D21: 10000 | E21: 10000 | F21: € par voiture et par an | G21: Calcul sur source | H21: Chiffre d’affaires « 2 M€ » ÷ « 200 voitures » en Occitanie. Coopérative à lucrativité limitée : les recettes couvrent à peu près les coûts. | I21: Ouvrir la source | J21: 2024
A22: R2 | B22: Voiture Citiz mise à disposition, tout compris | C22: 9000 | D22: 9000 | E22: 9000 | F22: € TTC par voiture et par an | G22: Calcul sur source | H22: « 750 € TTC / voiture / mois » facturé par Citiz × 12 mois | I22: Ouvrir la source | J22: 2021
A23: R3 | B23: Voiture Citiz mise à disposition (2016) | C23: 8520 | D23: 8520 | E23: 8520 | F23: € par voiture et par an | G23: Sourcé | H23: « Mise à disposition d’un véhicule CITIZ : 710€/mois soit 8 520€/an (voiture, location boitier, abonnement) » | I23: Ouvrir la source | J23: 2016
A24: R4 | B24: Frais fixes supportés par Citiz | C24: 3000 | D24: 3000 | E24: 3000 | F24: € par voiture et par an | G24: Calcul sur source | H24: « Les frais fixes supportés par CITIZ s’élèvent à 250 euros/mois/véhicule » × 12 | I24: Ouvrir la source | J24: jusqu’au 31/10/2024
A25: R5 | B25: Seuil de rentabilité d’une voiture, indiqué par Citiz | C25: 8400 | D25: 9600 | E25: 10800 | F25: € par voiture et par an | G25: Sourcé (Citiz) | H25: Réponse de Citiz à l’équipe (20/10/2026) : une voiture est rentable « entre 700/900 €/mois suivant le modèle des véhicules ainsi que l’emplacement ». × 12 mois. Défaut = milieu (800 € par mois). | I25: — | J25: 20/10/2026
A27: Chiffres en bleu = données d’entrée (modifiables). Lignes sur fond orange = hypothèses de l’équipe, sans source directe : à présenter comme telles au jury.
A28: Autres liens utiles : P4 haut (L’argus) https://www.largus.fr/prix-du-neuf/toyota/yaris-affaires.html ; Niort (bornes) https://www.niortagglo.fr/deliberations-agglo/CA_131123/C33-11-2023-19.pdf ; Livre blanc Citiz 2026 https://www.citiz.coop/uploads/2026/02/2026-CITIZ-livre_blanc.pdf

Sheet Calcul
A1: Poste | B1: Bas | C1: Défaut | D1: Haut | E1: Formule
A2: 1. INVESTISSEMENT D’UNE STATION (2 voitures)
A3: Aménagement de la place | B3: =Hypothèses!$C$4 -> 0 | C3: =Hypothèses!$D$4 -> 1200 | D3: =Hypothèses!$E$4 -> 1200 | E3: P2
A4: Boîtiers télématiques | B4: =Hypothèses!$C$5*Hypothèses!$C$3 -> 8000 | C4: =Hypothèses!$D$5*Hypothèses!$D$3 -> 8000 | D4: =Hypothèses!$E$5*Hypothèses!$E$3 -> 8000 | E4: P3 × P1
A5: Achat des voitures | B5: =Hypothèses!$C$6*Hypothèses!$C$3 -> 24000 | C5: =Hypothèses!$D$6*Hypothèses!$D$3 -> 48980 | D5: =Hypothèses!$E$6*Hypothèses!$E$3 -> 53000 | E5: P4 × P1
A6: Total investissement (station thermique ou hybride) | B6: =SUM(B3:B5) -> 32000 | C6: =SUM(C3:C5) -> 58180 | D6: =SUM(D3:D5) -> 62200 | E6: somme
A7: Option borne électrique (achat + installation) | B7: =Hypothèses!$C$18+Hypothèses!$C$19 -> 5800 | C7: =Hypothèses!$D$18+Hypothèses!$D$19 -> 7400 | D7: =Hypothèses!$E$18+Hypothèses!$E$19 -> 9000 | E7: P14 + P15
A8: Total investissement (station électrique) | B8: =B6+B7 -> 37800 | C8: =C6+C7 -> 65580 | D8: =D6+D7 -> 71200 | E8: avec borne
A9: 2. COÛT ANNUEL COMPLET PAR VOITURE
A10: Amortissement de la voiture | B10: =Hypothèses!$C$6/Hypothèses!$C$7 -> 2400 | C10: =Hypothèses!$D$6/Hypothèses!$D$7 -> 4898 | D10: =Hypothèses!$E$6/Hypothèses!$E$7 -> 5300 | E10: P4 ÷ P5
A11: Amortissement du boîtier | B11: =Hypothèses!$C$5/Hypothèses!$C$8 -> 800 | C11: =Hypothèses!$D$5/Hypothèses!$D$8 -> 800 | D11: =Hypothèses!$E$5/Hypothèses!$E$8 -> 800 | E11: P3 ÷ P6
A12: Assurance tous risques | B12: =Hypothèses!$C$10 -> 610 | C12: =Hypothèses!$D$10 -> 1102 | D12: =Hypothèses!$E$10 -> 2237 | E12: P7
A13: Entretien et réparations | B13: =Hypothèses!$C$11*Hypothèses!$C$12 -> 528 | C13: =Hypothèses!$D$11*Hypothèses!$D$12 -> 792 | D13: =Hypothèses!$E$11*Hypothèses!$E$12 -> 1056 | E13: P8 × P9
A14: Carburant | B14: =Hypothèses!$C$13*Hypothèses!$C$14/100*Hypothèses!$C$15 -> 1760.54 | C14: =Hypothèses!$D$13*Hypothèses!$D$14/100*Hypothèses!$D$15 -> 2031.062 | D14: =Hypothèses!$E$13*Hypothèses!$E$14/100*Hypothèses!$E$15 -> 2318.76 | E14: P10 × P11 ÷ 100 × P12
A15: Redevance de stationnement | B15: =Hypothèses!$C$16 -> 0 | C15: =Hypothèses!$D$16 -> 750 | D15: =Hypothèses!$E$16 -> 1500 | E15: P13 (1 place par voiture)
A16: Total des coûts identifiés par voiture | B16: =SUM(B10:B15) -> 6098.54 | C16: =SUM(C10:C15) -> 10373.062 | D16: =SUM(D10:D15) -> 13211.76 | E16: somme
A17: 3. COÛT ANNUEL COMPLET PAR STATION
A18: Voitures (coûts identifiés) | B18: =B16*Hypothèses!$C$3 -> 12197.08 | C18: =C16*Hypothèses!$D$3 -> 20746.124 | D18: =D16*Hypothèses!$E$3 -> 26423.52 | E18: total voiture × P1
A19: Amortissement de l’aménagement | B19: =Hypothèses!$C$4/Hypothèses!$C$8 -> 0 | C19: =Hypothèses!$D$4/Hypothèses!$D$8 -> 240 | D19: =Hypothèses!$E$4/Hypothèses!$E$8 -> 240 | E19: P2 ÷ P6
A20: Coût annuel complet par station (thermique ou hybride) | B20: =B18+B19 -> 12197.08 | C20: =C18+C19 -> 20986.124 | D20: =D18+D19 -> 26663.52 | E20: À DONNER À MSc 4
A21: Option : amortissement de la borne | B21: =B7/Hypothèses!$C$8 -> 1160 | C21: =C7/Hypothèses!$D$8 -> 1480 | D21: =D7/Hypothèses!$E$8 -> 1800 | E21: borne ÷ P6
A22: Coût annuel complet par station (électrique) | B22: =B20+B21 -> 13357.08 | C22: =C20+C21 -> 22466.124 | D22: =D20+D21 -> 28463.52 | E22: avec borne
A23: 4. COÛT DE LA PREMIÈRE ANNÉE (trésorerie)
A24: Investissement | B24: =B6 -> 32000 | C24: =C6 -> 58180 | D24: =D6 -> 62200 | E24: section 1
A25: Fonctionnement 1 an (hors amortissements) | B25: =(B12+B13+B14+B15)*Hypothèses!$C$3 -> 5797.08 | C25: =(C12+C13+C14+C15)*Hypothèses!$D$3 -> 9350.124 | D25: =(D12+D13+D14+D15)*Hypothèses!$E$3 -> 14223.52 | E25: (assurance + entretien + carburant + stationnement) × P1
A26: Total décaissé la première année | B26: =B24+B25 -> 37797.08 | C26: =C24+C25 -> 67530.124 | D26: =D24+D25 -> 76423.52 | E26: si Citiz achète les voitures comptant
A27: 5. VÉRIFICATION AVEC LES REPÈRES (par voiture et par an)
A28: Repère : recettes Citiz Occitanie par voiture | B28: =Hypothèses!$C$21 -> 10000 | C28: =Hypothèses!$D$21 -> 10000 | D28: =Hypothèses!$E$21 -> 10000 | E28: R1
A29: Repère : voiture Citiz mise à disposition (2021) | B29: =Hypothèses!$C$22 -> 9000 | C29: =Hypothèses!$D$22 -> 9000 | D29: =Hypothèses!$E$22 -> 9000 | E29: R2
A30: Repère : voiture Citiz mise à disposition (2016) | B30: =Hypothèses!$C$23 -> 8520 | C30: =Hypothèses!$D$23 -> 8520 | D30: =Hypothèses!$E$23 -> 8520 | E30: R3
A31: Repère : seuil de rentabilité indiqué par Citiz | B31: =Hypothèses!$C$25 -> 8400 | C31: =Hypothèses!$D$25 -> 9600 | D31: =Hypothèses!$E$25 -> 10800 | E31: R5 : 700 à 900 € par mois × 12
A32: Écart entre R1 et nos coûts identifiés | B32: =B28-B16 -> 3901.46 | C32: =C28-C16 -> -373.062 | D32: =D28-D16 -> -3211.76 | E32: R1 − total voiture : frais de structure non chiffrés (personnel, plateforme, assistance, nettoyage)
